webpipe/__init__.py
webpipe-0.0.0.dist-info/WHEEL
webpipe-0.0.0.dist-info/METADATA
webpipe-0.0.0.dist-info/RECORD
