Metadata-Version: 2.1
Name: webpipe
Version: 0.0.0
Summary: webpipe
License: MIT
Author: Nikhil Rao
Author-email: nikhil@webpipe.io
Requires-Python: >=3.10,<4.0
Classifier: License :: OSI Approved :: MIT License
Classifier: Programming Language :: Python :: 3
Classifier: Programming Language :: Python :: 3.10
